setup.cfg
setup.py
probe/__init__.py
probe/api_client.py
probe/configuration.py
probe/rest.py
probe/tests.py
probe/apis/__init__.py
probe/apis/company_api.py
probe/apis/search_api.py
probe/models/__init__.py
probe/models/address.py
probe/models/authorized_signatories.py
probe/models/authorized_signatory.py
probe/models/authorized_signatory_with_companies.py
probe/models/charge.py
probe/models/charges.py
probe/models/companies.py
probe/models/company_authorized_signatories.py
probe/models/company_brief.py
probe/models/company_detail.py
probe/models/company_detail_company.py
probe/models/financial_data_status.py
probe/models/financial_data_status_datastatus.py
probe/models/financials.py
probe/models/inline_response_200.py
probe/models/inline_response_200_1.py
probe/models/inline_response_200_2.py
probe/models/inline_response_200_3.py
probe/models/inline_response_200_4.py
probe/models/inline_response_200_5.py
probe/models/inline_response_200_6.py
probe/models/metadata.py
probe/models/yearly_financials.py
probe_py.egg-info/PKG-INFO
probe_py.egg-info/SOURCES.txt
probe_py.egg-info/dependency_links.txt
probe_py.egg-info/requires.txt
probe_py.egg-info/top_level.txt