Metadata-Version: 1.0
Name: probe-py
Version: 1.1.2
Summary: Probe API Client
Home-page: https://github.com/loanzen/probe-py
Author: UNKNOWN
Author-email: suraj@loanzen.in
License: UNKNOWN
Keywords: Probe API
Platform: UNKNOWN
